nanoconfig/__init__.py
nanoconfig/cli.py
nanoconfig/options.py
nanoconfig/utils.py
nanoconfig/data/__init__.py
nanoconfig/data/fs.py
nanoconfig/data/generator.py
nanoconfig/data/huggingface.py
nanoconfig/data/source.py
nanoconfig/data/torch.py
nanoconfig/data/transform.py
nanoconfig/data/utils.py
nanoconfig/data/visualizer.py
nanoconfig/experiment/__init__.py
nanoconfig/experiment/clearml.py
nanoconfig/experiment/wandb.py
nanoconfig/experiment/util/clearml_launcher.py
nanoconfig-0.1.1.dist-info/METADATA
nanoconfig-0.1.1.dist-info/WHEEL
nanoconfig-0.1.1.dist-info/entry_points.txt
nanoconfig-0.1.1.dist-info/RECORD
